LICENSE
README.md
setup.cfg
setup.py
packagenlp/__init__.py
packagenlp/analyse.py
packagenlp/nlp.py
packagenlp.egg-info/PKG-INFO
packagenlp.egg-info/SOURCES.txt
packagenlp.egg-info/dependency_links.txt
packagenlp.egg-info/requires.txt
packagenlp.egg-info/top_level.txt
packagenlp/data/Logo_B_D.png
packagenlp/data/image.jpg
packagenlp/resources/TreeTagger.zip
tests/tests.py