Metadata-Version: 2.1
Name: packagenlp
Version: 0.0.52
Summary: A package for NLP
Download-URL: https://gitlab.com/business-decision-data-science/packagenlp/-/package_files/82622627/download
Author: Business & Decision
Keywords: NLP,Français,Langues,Traitements
Classifier: Programming Language :: Python :: 3
Classifier: License :: OSI Approved :: MIT License
Classifier: Operating System :: OS Independent
Requires-Python: >=3.6
License-File: LICENSE
Requires-Dist: pandas
Requires-Dist: nltk
Requires-Dist: spacy
Requires-Dist: unidecode
Requires-Dist: treetaggerwrapper
Requires-Dist: streamlit
Requires-Dist: plotly
Requires-Dist: wordcloud
